cbr_client.py
cbr_client-0.4.0.dist-info/licenses/LICENSE
cbr_client-0.4.0.dist-info/METADATA
cbr_client-0.4.0.dist-info/WHEEL
cbr_client-0.4.0.dist-info/top_level.txt
cbr_client-0.4.0.dist-info/RECORD
