Metadata-Version: 2.4
Name: cbr-client
Version: 0.4.0
Summary: Tool for easy working with https://portal5.cbr.ru API
Home-page: https://github.com/mrslow/cbr-client
Author: Anton Shchetikhin
Author-email: animal2k@gmail.com
License: MIT
Keywords: cbr rest api client
Classifier: License :: OSI Approved :: MIT License
Classifier: Programming Language :: Python :: 3
Classifier: Programming Language :: Python :: 3.7
Classifier: Programming Language :: Python :: 3.8
Classifier: Programming Language :: Python :: 3.9
Classifier: Programming Language :: Python :: 3.10
Requires-Python: >=3.7
License-File: LICENSE
Requires-Dist: httpx
Requires-Dist: pydantic
Dynamic: author
Dynamic: author-email
Dynamic: classifier
Dynamic: description
Dynamic: description-content-type
Dynamic: home-page
Dynamic: keywords
Dynamic: license
Dynamic: license-file
Dynamic: requires-dist
Dynamic: requires-python
Dynamic: summary
